{
  "status": "SUCCESS",
  "message": "Inference Done",
  "type": "LLAMA",
  "timestamp": "Fri Jan 16 08:13:26 PM UTC 2026",
  "data": {
    "response": "I'm happy to help with a stress test! However, I need more information about what you're looking for. Are you referring to a stress test in the context of finance or cybersecurity? Or perhaps you're looking for a physical exercise challenge?\n\nTo get started, could you please provide more context or clarify which type of stress test you're interested in?"
  }
}
