{
  "status": "SUCCESS",
  "message": "Inference Done",
  "type": "LLAMA",
  "timestamp": "Sat Jan 17 04:28:50 AM UTC 2026",
  "data": {
    "response": "I'd be happy to help with the stress test. Since I don't have any specific information about what you're referring to, I'll provide a general response.\n\nA stress test is typically used to evaluate an individual's or system's ability to handle increased loads or pressures. In the context of your request, here are a few possible interpretations:\n\n1. **Financial stress test**: A financial stress test evaluates an individual's or organization's ability to withstand economic downturns, job losses, or other financial shocks.\n2. **Physical fitness stress test**: A physical fitness stress test measures an individual's cardiovascular and respiratory response to exercise, such as running or cycling.\n3. **System stress testing**: A system stress test, like the one used in software development, simulates high traffic or load on a system to evaluate its performance, scalability, and reliability.\n\nTo proceed with your original request (stress test #18), could you please provide more context or clarify which type of stress test you're referring to?"
  }
}
