{
  "status": "SUCCESS",
  "message": "Inference Done",
  "type": "LLAMA",
  "timestamp": "Sat Jan 17 06:36:25 AM UTC 2026",
  "data": {
    "response": "**Summary of Quantum Computing**\n\nQuantum computing is a revolutionary technology that uses the principles of quantum mechanics to perform calculations and operations on data. Unlike classical computers, which use bits to store and process information as either 0 or 1, quantum computers use qubits (quantum bits) that can exist in multiple states simultaneously.\n\n**Key Principles:**\n\n1. **Superposition**: Qubits can exist in a state of superposition, where they can represent both 0 and 1 at the same time.\n2. **Entanglement**: Qubits can become entangled, meaning their properties are correlated, even when separated by large distances.\n3. **Quantum gates**: Quantum computers use quantum gates to perform operations on qubits, similar to how classical computers use logic gates.\n\n**Advantages:**\n\n1. **Exponential scaling**: Quantum computers can solve certain problems much faster than classical computers, thanks to the exponential scaling of qubit numbers.\n2. **Simulations**: Quantum computers can simulate complex systems and materials, which could lead to breakthroughs in fields like chemistry and materials science.\n3. **Cryptography**: Quantum computers can potentially break certain encryption algorithms currently in use, but they also offer new quantum-resistant cryptographic techniques.\n\n**Challenges:**\n\n1. **Error correction**: Quantum computers are prone to errors due to the fragile nature of qubits, which require sophisticated error correction techniques to mitigate.\n2. **Scalability**: Currently, most quantum computers are small-scale and require significant resources to scale up to practical sizes.\n3. **Quantum noise**: Qubits are susceptible to environmental noise, which can cause errors and limit their performance.\n\n**Applications:**\n\n1. **Cryptography**: Quantum-resistant cryptography techniques like quantum key distribution (QKD) are being developed for secure communication.\n2. **Optimization**: Quantum computers can solve complex optimization problems efficiently, with applications in fields like logistics and finance.\n3. **Simulation**: Quantum simulators can accurately model complex systems, leading to breakthroughs in chemistry, materials science, and pharmaceutical research.\n\n**Current Status:**\n\nWhile quantum computing is still in its early stages, significant progress has been made in recent years. Companies like Google, IBM, Microsoft, and Rigetti Computing are actively developing quantum computers for various applications. Research institutions and universities are also exploring the potential of quantum computing to tackle some of humanity's most pressing challenges.\n\n**Conclusion:**\n\nQuantum computing is a rapidly evolving field with vast potential to transform various industries. While significant technical hurdles remain, researchers and developers continue to make progress in designing, building, and testing quantum computers. As the field advances, we can expect new applications and breakthroughs to emerge, transforming our understanding of the world and unlocking new possibilities for human innovation."
  }
}
