{
  "status": "SUCCESS",
  "message": "Inference Done",
  "type": "LLAMA",
  "timestamp": "Sat Jan 17 06:14:19 AM UTC 2026",
  "data": {
    "response": "**Summary of Quantum Computing**\n\nQuantum computing is a revolutionary technology that uses the principles of quantum mechanics to perform calculations and operations on data. It has the potential to solve complex problems that are currently unsolvable or require an unfeasible amount of time to solve classically.\n\n**Key Principles:**\n\n1. **Superposition**: Quantum computers can exist in multiple states simultaneously, allowing them to process multiple possibilities at once.\n2. **Entanglement**: Quantum bits (qubits) can be connected in such a way that the state of one qubit is dependent on the state of the other, even when separated by large distances.\n3. **Quantum Measurement**: When a qubit is measured, its state collapses to one specific value, which can be either 0 or 1.\n\n**How Quantum Computing Works:**\n\n1. **Qubits**: Qubits are the fundamental units of quantum computing, similar to classical bits but with additional properties that allow them to exist in multiple states at once.\n2. **Quantum Gates**: Quantum gates are the quantum equivalent of logic gates in classical computing, used to manipulate qubits and perform calculations.\n3. **Quantum Algorithms**: Quantum algorithms are designed specifically for quantum computers and take advantage of their unique properties to solve problems that are difficult or impossible for classical computers.\n\n**Applications:**\n\n1. **Cryptography**: Quantum computers can break certain classical encryption algorithms, but they can also be used to create new, unbreakable encryption methods.\n2. **Optimization**: Quantum computers can quickly find the optimal solution to complex optimization problems in fields like logistics and finance.\n3. **Simulation**: Quantum computers can simulate complex systems, such as molecules and chemical reactions, which could lead to breakthroughs in fields like medicine and materials science.\n\n**Challenges and Limitations:**\n\n1. **Error Correction**: Quantum computers are prone to errors due to the fragile nature of qubits, making it essential to develop robust error correction techniques.\n2. **Scalability**: Currently, most quantum computers are small-scale and require significant resources to operate at larger scales.\n3. **Quantum Noise**: The noisy nature of quantum systems can interfere with calculations, making it challenging to achieve reliable results.\n\n**Future Outlook:**\n\n1. **Advances in Materials Science**: Research is ongoing to develop new materials and technologies that can improve the coherence and stability of qubits.\n2. **Development of Quantum Algorithms**: New algorithms are being designed to take advantage of quantum computing's unique properties, such as quantum supremacy and near-term algorithms for optimization and simulation.\n3. **Quantum-Classical Hybrids**: Researchers are exploring ways to combine classical and quantum computing to create more powerful and efficient systems.\n\nIn conclusion, quantum computing has the potential to revolutionize various fields by solving complex problems that are currently unsolvable or require an unfeasible amount of time to solve classically. However, significant challenges need to be addressed to overcome current limitations and unlock its full potential."
  }
}
