{
  "status": "SUCCESS",
  "message": "Inference Done",
  "type": "LLAMA",
  "timestamp": "Sat Jan 17 06:25:17 AM UTC 2026",
  "data": {
    "response": "**Summary of Quantum Computing**\n\nQuantum computing is a revolutionary technology that leverages the principles of quantum mechanics to perform calculations and operations on data. It has the potential to solve complex problems that are intractable or require an unfeasible amount of time with classical computers.\n\n**Key Features:**\n\n1. **Quantum Bits (Qubits):** Qubits are the fundamental units of quantum computing, which can exist in multiple states simultaneously (superposition) and entangled with each other.\n2. **Quantum Gate Operations:** Quantum gates are the quantum equivalent of logic gates in classical computing. They perform operations on qubits to manipulate and control their state.\n3. **Superposition:** Qubits can exist in multiple states at once, allowing for parallel processing and exponential scaling in certain computations.\n4. **Entanglement:** Qubits can become entangled, enabling the transfer of information between them without physical contact.\n\n**Advantages:**\n\n1. **Exponential Scaling:** Quantum computers can solve certain problems exponentially faster than classical computers, making them suitable for complex simulations and optimization tasks.\n2. **Simulation and Modeling:** Quantum computers can accurately simulate complex systems and chemical reactions, leading to breakthroughs in fields like chemistry and materials science.\n3. **Cryptography and Cybersecurity:** Quantum computers have the potential to break certain types of encryption algorithms used today, but they also enable new cryptographic techniques that are resistant to quantum attacks.\n\n**Challenges:**\n\n1. **Error Correction:** Quantum computers are prone to errors due to the fragile nature of qubits. Developing robust error correction methods is essential for large-scale quantum computing.\n2. **Quantum Noise and Interference:** Quantum systems are sensitive to noise, interference, and other environmental factors that can disrupt computation.\n3. **Scalability and Control:** As the number of qubits increases, control over the system becomes more challenging.\n\n**Current State:**\n\n1. **Early-Stage Applications:** Quantum computing has been applied in various domains, such as chemistry, materials science, and machine learning, with promising results.\n2. **Experimentation and Development:** Companies like Google, IBM, Microsoft, and Rigetti Computing are actively developing quantum computing hardware and software.\n\n**Future Prospects:**\n\n1. **Advancements in Hardware:** Improvements in qubit quality, coherence times, and scalability will be crucial for large-scale quantum computing.\n2. **Software and Algorithm Development:** Developing practical algorithms and software frameworks that can take advantage of quantum computing's unique capabilities is essential.\n3. **Integration with Classical Computing:** Seamlessly integrating quantum computing with classical computing systems will require significant advancements in interfaces, communication protocols, and data exchange.\n\nQuantum computing holds immense potential to solve complex problems and revolutionize various fields, but significant technical challenges need to be addressed before it becomes a mainstream technology."
  }
}
